async_doh/__init__.py
async_doh/client/__init__.py
async_doh/client/__main__.py
async_doh/client/client.py
async_doh/client/resolver_patch.py
async_doh/client/session.py
async_doh/server/__init__.py
async_doh/server/__main__.py
async_doh-0.3.0.dist-info/WHEEL
async_doh-0.3.0.dist-info/METADATA
async_doh-0.3.0.dist-info/RECORD
