Metadata-Version: 2.1
Name: async-doh
Version: 0.3.0
Summary: DNS over HTTPS based on aiohttp and async_dns
Home-page: https://github.com/gera2ld/async-doh
License: MIT
Keywords: async,dns,asyncio,doh
Author: Gerald
Author-email: gera2ld@live.com
Requires-Python: >=3.7,<4.0
Classifier: License :: OSI Approved :: MIT License
Classifier: Programming Language :: Python :: 3
Classifier: Programming Language :: Python :: 3.7
Classifier: Programming Language :: Python :: 3.8
Classifier: Programming Language :: Python :: 3.9
Requires-Dist: aiohttp (>=3.6.2,<4.0.0)
Requires-Dist: async_dns (>=2.0.0,<3.0.0)
Project-URL: Repository, https://github.com/gera2ld/async-doh
